StreamProcessingWithApacheFlinkZhongwenbanFix1/README.md
StreamProcessingWithApacheFlinkZhongwenbanFix1/__init__.py
StreamProcessingWithApacheFlinkZhongwenbanFix1/__main__.py
StreamProcessingWithApacheFlinkZhongwenbanFix1/file.epub
StreamProcessingWithApacheFlinkZhongwenbanFix1/index.html
StreamProcessingWithApacheFlinkZhongwenbanFix1/css/__init__.py
StreamProcessingWithApacheFlinkZhongwenbanFix1/css/annotations.css
StreamProcessingWithApacheFlinkZhongwenbanFix1/css/main.css
StreamProcessingWithApacheFlinkZhongwenbanFix1/css/normalize.css
StreamProcessingWithApacheFlinkZhongwenbanFix1/css/popup.css
StreamProcessingWithApacheFlinkZhongwenbanFix1/font/__init__.py
StreamProcessingWithApacheFlinkZhongwenbanFix1/font/fontello.eot
StreamProcessingWithApacheFlinkZhongwenbanFix1/font/fontello.svg
StreamProcessingWithApacheFlinkZhongwenbanFix1/font/fontello.ttf
StreamProcessingWithApacheFlinkZhongwenbanFix1/font/fontello.woff
StreamProcessingWithApacheFlinkZhongwenbanFix1/img/__init__.py
StreamProcessingWithApacheFlinkZhongwenbanFix1/img/annotator-glyph-sprite.png
StreamProcessingWithApacheFlinkZhongwenbanFix1/img/annotator-icon-sprite.png
StreamProcessingWithApacheFlinkZhongwenbanFix1/img/apple-touch-icon.png
StreamProcessingWithApacheFlinkZhongwenbanFix1/img/cancelfullscreen.png
StreamProcessingWithApacheFlinkZhongwenbanFix1/img/close.png
StreamProcessingWithApacheFlinkZhongwenbanFix1/img/fullscreen.png
StreamProcessingWithApacheFlinkZhongwenbanFix1/img/loader.gif
StreamProcessingWithApacheFlinkZhongwenbanFix1/img/menu-icon.png
StreamProcessingWithApacheFlinkZhongwenbanFix1/img/save.png
StreamProcessingWithApacheFlinkZhongwenbanFix1/img/saved.png
StreamProcessingWithApacheFlinkZhongwenbanFix1/img/settings-s.png
StreamProcessingWithApacheFlinkZhongwenbanFix1/img/settings.png
StreamProcessingWithApacheFlinkZhongwenbanFix1/img/star.png
StreamProcessingWithApacheFlinkZhongwenbanFix1/js/__init__.py
StreamProcessingWithApacheFlinkZhongwenbanFix1/js/epub.js
stream_processing_with_apache_flink_zhongwenban_fix1-2025.3.25.1.dist-info/METADATA
stream_processing_with_apache_flink_zhongwenban_fix1-2025.3.25.1.dist-info/WHEEL
stream_processing_with_apache_flink_zhongwenban_fix1-2025.3.25.1.dist-info/entry_points.txt
stream_processing_with_apache_flink_zhongwenban_fix1-2025.3.25.1.dist-info/top_level.txt
stream_processing_with_apache_flink_zhongwenban_fix1-2025.3.25.1.dist-info/RECORD
